pycsp3/__init__.py
pycsp3/compiler.py
pycsp3/dashboard.py
pycsp3/functions.py
pycsp3/version.txt
pycsp3/classes/__init__.py
pycsp3/classes/entities.py
pycsp3/classes/nodes.py
pycsp3/classes/auxiliary/__init__.py
pycsp3/classes/auxiliary/conditions.py
pycsp3/classes/auxiliary/diagrams.py
pycsp3/classes/auxiliary/enums.py
pycsp3/classes/auxiliary/tables.py
pycsp3/classes/main/__init__.py
pycsp3/classes/main/annotations.py
pycsp3/classes/main/constraints.py
pycsp3/classes/main/objectives.py
pycsp3/classes/main/variables.py
pycsp3/libs/__init__.py
pycsp3/libs/forbiddenfruit/__init__.py
pycsp3/parser/__init__.py
pycsp3/parser/callbacks.py
pycsp3/parser/constants.py
pycsp3/parser/methods.py
pycsp3/parser/xentries.py
pycsp3/parser/xparser.py
pycsp3/problems/README.md
pycsp3/problems/__init__.py
pycsp3/problems/data/__init__.py
pycsp3/problems/data/parsing.py
pycsp3/solvers/__init__.py
pycsp3/solvers/solver.py
pycsp3/solvers/ace/ACE-2.5.jar
pycsp3/solvers/ace/__init__.py
pycsp3/solvers/ace/ace.py
pycsp3/solvers/choco/__init__.py
pycsp3/solvers/choco/choco-parsers-4.10.15-beta.jar
pycsp3/solvers/choco/choco.py
pycsp3/solvers/external/__init__.py
pycsp3/solvers/external/external.py
pycsp3/tools/__init__.py
pycsp3/tools/aggregator.py
pycsp3/tools/compactor.py
pycsp3/tools/curser.py
pycsp3/tools/inspector.py
pycsp3/tools/slider.py
pycsp3/tools/utilities.py
pycsp3/tools/xcsp.py
pycsp3-2.5.dist-info/LICENSE
pycsp3-2.5.dist-info/METADATA
pycsp3-2.5.dist-info/WHEEL
pycsp3-2.5.dist-info/top_level.txt
pycsp3-2.5.dist-info/RECORD
