Metadata-Version: 2.2
Name: pycsp3
Version: 2.5
Summary: Modeling Constrained Combinatorial Problems in Python
Author: Lecoutre Christophe, Szczepanski Nicolas
Author-email: lecoutre@cril.fr, szczepanski@cril.fr
Maintainer: Szczepanski Nicolas
Maintainer-email: szczepanski@cril.fr
License: MIT
Project-URL: Documentation, https://pycsp.org/
Project-URL: Installation, http://pycsp.org/documentation/installation
Project-URL: Models and Data, http://pycsp.org/models/
Project-URL: Git, https://github.com/xcsp3team/pycsp3
Keywords: IA CP constraint modeling CSP COP
Platform: LINUX
Classifier: Topic :: Scientific/Engineering :: Artificial Intelligence
Classifier: Topic :: Education
Requires-Python: >=3
License-File: LICENSE
Requires-Dist: lxml
Dynamic: author
Dynamic: author-email
Dynamic: classifier
Dynamic: description
Dynamic: description-content-type
Dynamic: keywords
Dynamic: license
Dynamic: maintainer
Dynamic: maintainer-email
Dynamic: platform
Dynamic: project-url
Dynamic: requires-dist
Dynamic: requires-python
Dynamic: summary
